{"blt2f1c9cd011fd5637":{"title":"A Curated Collection","media":{"image":"","metadata":{"alt":"Ep. 5 | Mind The Gap","caption":"Nils Mindnich Takes On Chad’s Gap"},"video":null},"content":{"texts":[{"type":"doc","attrs":{"dirty":true},"children":[{"type":"p","attrs":{"dirty":true},"children":[{"text":"Rio’s Warmup & Recover Capsule"}]},{"type":"p","attrs":{"dirty":true},"children":[{"text":"Effortless Comfort Meets Unrestricted Mobility"}]}],"_version":5}],"link":"/shop","ctas":[{"link":{"title":"Get it!","href":"/cta-sunglasses"},"_metadata":{"uid":"cs152283f2283e63e2"},"style":"outline"}],"background_color":{"value":"bg.brand"}},"product_list":[{"uid":"bltb3db8d351bd912d1","_content_type_uid":"product_list"}],"tracking":{"promo_id":"202403_SunglassesTest","name":"2024.03 - Sunglasses Test"},"tags":[],"locale":"en-us","uid":"blt2f1c9cd011fd5637","ACL":{},"_version":5,"_in_progress":false,"sourceEntryFilePath":"C:\\Users\\Shreyas Bhoyar\\Desktop\\migration-aem\\_backup_474\\entries\\curated_collection\\en-us\\6e4c8990-054b-43fa-bd75-63002837d13c-entries.json","entryOldUid":"blt2f1c9cd011fd5637"}}